setup.py
kegmeter/__init__.py
kegmeter/common/Config.py
kegmeter/common/DBClient.py
kegmeter/common/Untappd.py
kegmeter/common/__init__.py
kegmeter/common/setup.py
kegmeter_common.egg-info/PKG-INFO
kegmeter_common.egg-info/SOURCES.txt
kegmeter_common.egg-info/dependency_links.txt
kegmeter_common.egg-info/namespace_packages.txt
kegmeter_common.egg-info/requires.txt
kegmeter_common.egg-info/top_level.txt