Metadata-Version: 1.0
Name: kegmeter-common
Version: 0.99.2
Summary: Kegmeter libraries used by both the app and the webserver
Home-page: https://github.com/Dennovin/kegmeter
Author: OmniTI Computer Consulting, Inc.
Author-email: hello@omniti.com
License: MIT
Platform: UNKNOWN
